Metadata-Version: 2.1
Name: anmoku
Version: 1.0.0
Summary: A peaceful and fully typed MyAnimeList/Jikan API wrapper with caching and proper rate limiting.
Author-email: Goldy <goldy@devgoldy.xyz>, EmreTech <emreterzioglu49@gmail.com>
License: MIT License
Project-URL: GitHub, https://github.com/THEGOLDENPRO/anmoku
Project-URL: BugTracker, https://github.com/THEGOLDENPRO/anmoku/issues
Keywords: anime api wrapper,mal,myanimelist,My Anime List,jikan api wrapper,async anime api wrapper,jikan caching,jikan rate limiting
Classifier: Operating System :: Microsoft :: Windows :: Windows 11
Classifier: Operating System :: Microsoft :: Windows :: Windows 10
Classifier: Operating System :: POSIX :: Linux
Classifier: License :: OSI Approved :: MIT License
Classifier: Programming Language :: Python :: 3.8
Classifier: Programming Language :: Python :: 3.9
Classifier: Programming Language :: Python :: 3.10
Classifier: Programming Language :: Python :: 3.11
Requires-Python: >=3.8
License-File: LICENSE
Requires-Dist: typing-extensions
Requires-Dist: devgoldyutils >=2.5.6
Requires-Dist: requests
Requires-Dist: aiohttp
Requires-Dist: Pillow
Requires-Dist: importlib-metadata ; python_version < "3.8"
Provides-Extra: dev
Requires-Dist: ruff ; extra == 'dev'
Requires-Dist: build ; extra == 'dev'
Requires-Dist: pytest ; extra == 'dev'
Requires-Dist: pytest-asyncio ; extra == 'dev'
